awslabs/__init__.py
awslabs/py.typed
awslabs/document_loader_mcp_server/__init__.py
awslabs/document_loader_mcp_server/server.py
awslabs_document_loader_mcp_server-1.0.8.dist-info/METADATA
awslabs_document_loader_mcp_server-1.0.8.dist-info/WHEEL
awslabs_document_loader_mcp_server-1.0.8.dist-info/entry_points.txt
awslabs_document_loader_mcp_server-1.0.8.dist-info/licenses/LICENSE
awslabs_document_loader_mcp_server-1.0.8.dist-info/licenses/NOTICE
awslabs_document_loader_mcp_server-1.0.8.dist-info/RECORD
